masterblaster/__init__.py
masterblaster/gameaccount.py
masterblaster/headers.py
masterblaster/image.py
masterblaster/masterblaster.py
masterblaster/match.py
masterblaster/member.py
masterblaster/organisation.py
masterblaster/player.py
masterblaster/py.typed
masterblaster/schedule.py
masterblaster/team.py
masterblaster_py-0.1.0rc9.dist-info/LICENSE
masterblaster_py-0.1.0rc9.dist-info/METADATA
masterblaster_py-0.1.0rc9.dist-info/WHEEL
masterblaster_py-0.1.0rc9.dist-info/RECORD
