Metadata-Version: 2.1
Name: masterblaster.py
Version: 0.1.0rc9
Summary: Python API wrapper for masterblaster.gg
Home-page: https://github.com/Askepios-ai/masterblaster.py
Author: Øyvind Nohr
Author-email: oeyvindnohr@gmail.com
Requires-Python: >=3.10,<4.0
Classifier: License :: OSI Approved :: MIT License
Classifier: Programming Language :: Python :: 3
Classifier: Programming Language :: Python :: 3.10
Classifier: Programming Language :: Python :: 3.11
Requires-Dist: aiohttp (>=3.10.1,<4.0.0)
Requires-Dist: python-dateutil (>=2.9.0.post0,<3.0.0)
Project-URL: Documentation, https://masterblasterpy.readthedocs.io/en/latest/
Project-URL: Repository, https://github.com/Askepios-ai/masterblaster.py
